onnx2bnn/__init__.py
onnx2bnn/__main__.py
onnx2bnn/_onnx2bnn.cpython-37m-darwin.so
onnx2bnn/convert.py
onnx2bnn-0.1.7.dist-info/METADATA
onnx2bnn-0.1.7.dist-info/WHEEL
onnx2bnn-0.1.7.dist-info/top_level.txt
onnx2bnn-0.1.7.dist-info/RECORD
