Metadata-Version: 2.1
Name: onnx2bnn
Version: 0.1.7
Summary: Convert ONNX to dabnn
Home-page: https://github.com/JDAI-CV/dabnn
Author: daquexian
Author-email: daquexian566@gmail.com
License: UNKNOWN
Platform: UNKNOWN
Requires-Dist: onnx
